table_transformer/__init__.py
table_transformer/.github/workflows/codeql-analysis.yml
table_transformer/detr/Dockerfile
table_transformer/detr/LICENSE
table_transformer/detr/README.md
table_transformer/detr/engine.py
table_transformer/detr/engine_multi.py
table_transformer/detr/hubconf.py
table_transformer/detr/main.py
table_transformer/detr/requirements.txt
table_transformer/detr/run_with_submitit.py
table_transformer/detr/test_all.py
table_transformer/detr/tox.ini
table_transformer/detr/.circleci/config.yml
table_transformer/detr/__pycache__/engine.cpython-310.pyc
table_transformer/detr/d2/README.md
table_transformer/detr/d2/converter.py
table_transformer/detr/d2/train_net.py
table_transformer/detr/d2/configs/detr_256_6_6_torchvision.yaml
table_transformer/detr/d2/configs/detr_segm_256_6_6_torchvision.yaml
table_transformer/detr/d2/detr/__init__.py
table_transformer/detr/d2/detr/config.py
table_transformer/detr/d2/detr/dataset_mapper.py
table_transformer/detr/d2/detr/detr.py
table_transformer/detr/datasets/__init__.py
table_transformer/detr/datasets/coco.py
table_transformer/detr/datasets/coco_eval.py
table_transformer/detr/datasets/coco_panoptic.py
table_transformer/detr/datasets/panoptic_eval.py
table_transformer/detr/datasets/transforms.py
table_transformer/detr/datasets/__pycache__/__init__.cpython-310.pyc
table_transformer/detr/datasets/__pycache__/coco.cpython-310.pyc
table_transformer/detr/datasets/__pycache__/coco_eval.cpython-310.pyc
table_transformer/detr/datasets/__pycache__/panoptic_eval.cpython-310.pyc
table_transformer/detr/datasets/__pycache__/transforms.cpython-310.pyc
table_transformer/detr/models/__init__.py
table_transformer/detr/models/backbone.py
table_transformer/detr/models/detr.py
table_transformer/detr/models/detr_multi.py
table_transformer/detr/models/matcher.py
table_transformer/detr/models/position_encoding.py
table_transformer/detr/models/segmentation.py
table_transformer/detr/models/transformer.py
table_transformer-1.0.6.dist-info/LICENSE
table_transformer-1.0.6.dist-info/METADATA
table_transformer-1.0.6.dist-info/WHEEL
table_transformer-1.0.6.dist-info/top_level.txt
table_transformer-1.0.6.dist-info/RECORD
