Metadata-Version: 2.1
Name: table_transformer
Version: 1.0.6
Summary: Table Transformer
Classifier: Programming Language :: Python :: 3
Classifier: License :: OSI Approved :: MIT License
Classifier: Operating System :: OS Independent
Requires-Python: >=3.10
License-File: LICENSE
Requires-Dist: torchvision (~=0.19.1)
Requires-Dist: numpy (~=2.1.1)
Requires-Dist: pandas (==2.2.2)
Requires-Dist: torch (~=2.4.1)
Requires-Dist: matplotlib (~=3.9.2)
Requires-Dist: seaborn (~=0.13.2)
Requires-Dist: PyMuPDF (==1.24.10)
Requires-Dist: scikit-image (==0.24.0)
Requires-Dist: pathlib (~=1.0.1)
Requires-Dist: pycocotools (~=2.0.7)
Requires-Dist: editdistance (==0.8.1)
Requires-Dist: scipy (~=1.14.1)
Requires-Dist: Cython (==0.29.33)
Requires-Dist: packaging (~=23.1)
Requires-Dist: tqdm (==4.66.5)
Requires-Dist: Pillow (~=9.5.0)
Requires-Dist: wheel (~=0.40.0)
Requires-Dist: easyocr (~=1.7.1)
